device_picker/DevicePicker.py
device_picker/__init__.py
device_picker-0.1.2.dist-info/METADATA
device_picker-0.1.2.dist-info/WHEEL
device_picker-0.1.2.dist-info/RECORD
