Metadata-Version: 2.1
Name: device-picker
Version: 0.1.2
Summary: A device picker for machine learning frameworks like PyTorch, TensorFlow, and JAX.
License: MIT
Author: Yinying Yao
Author-email: yaoyy.hi@gmail.com
Requires-Python: >=3.7,<4.0
Classifier: License :: OSI Approved :: MIT License
Classifier: Programming Language :: Python :: 3
Classifier: Programming Language :: Python :: 3.7
Classifier: Programming Language :: Python :: 3.8
Classifier: Programming Language :: Python :: 3.9
Classifier: Programming Language :: Python :: 3.10
Classifier: Programming Language :: Python :: 3.11
Classifier: Programming Language :: Python :: 3.12
Provides-Extra: jax-metal-support
Provides-Extra: jax-support
Provides-Extra: tensorflow-metal-support
Provides-Extra: tensorflow-support
Provides-Extra: torch-support
Requires-Dist: jax (>0.3.15) ; extra == "jax-support" or extra == "jax-metal-support"
Requires-Dist: jax-metal (>0.0.4) ; (sys_platform == "darwin" and platform_machine == "arm64") and (extra == "jax-metal-support")
Requires-Dist: tensorflow (>2.5.0) ; extra == "tensorflow-support" or extra == "tensorflow-metal-support"
Requires-Dist: tensorflow-metal (>0.8.0) ; (sys_platform == "darwin" and platform_machine == "arm64") and (extra == "tensorflow-metal-support")
Requires-Dist: torch (>1.8.1) ; extra == "torch-support"
